Workbook

Sheet Investment Assumptions
A1: Item | B1: Value
A2: Monthly active users | B2: ~1000
A3: Cost per user | B3: 5 PKR
A4: Server cost | B4: 7000 PKR/month
A5: Graphic Designer | B5: 0(self)
A6: Front end Developer cost | B6: 0(self)
A7: Developer cost | B7: 0 (student project)
A8: Premium Cost(1st year 1st semi) | B8: 300 per month
A9: Premium Cost(1st year 2nd semi) | B9: 480 per month
A10: Premium Cost(2st year 1st semi) | B10: 900 per month
A11: Premium Cost(2nd year 2nd semi) | B11: 1100 per month
A12: Monetization model | B12: Ads + premium features
... A15: Total Cost per month | B15: (CPI*200) + 7000

Sheet Year 1 Forecast
A1: Month | B1: Number of Users Attracted | C1: Total Users | D1: Users attracted via adds(CPI) | E1: Subscriptions bought | F1: Revenue Generated | G1: Outflow of cash | H1: Profit
A2: January | B2: 50 | C2: 50 | D2: 39 | E2: 2 | F2: =((B2-E2)*150)+(300*E2) -> 7800 | G2: =7000+(200*D2) -> 14800 | H2: =F2-G2 -> -7000
A3: February | B3: =C3-C2 -> 150 | C3: 200 | D3: 67 | E3: 12 | F3: =((B3-E3)*150)+(300*E3) -> 24300 | G3: =7000+(200*D3) -> 20400 | H3: =F3-G3 -> 3900
A4: March | B4: =C4-C3 -> 275 | C4: 475 | D4: 158 | E4: 25 | F4: =((B4-E4)*150)+(300*E4) -> 45000 | G4: =7000+(200*D4) -> 38600 | H4: =F4-G4 -> 6400
A5: April | B5: =C5-C4 -> 45 | C5: 520 | D5: 10 | E5: 3 | F5: =((B5-E5)*150)+(300*E5) -> 7200 | G5: =7000+(200*D5) -> 9000 | H5: =F5-G5 -> -1800
A6: May | B6: =C6-C5 -> 123 | C6: 643 | D6: 50 | E6: 14 | F6: =((B6-E6)*150)+(300*E6) -> 20550 | G6: =7000+(200*D6) -> 17000 | H6: =F6-G6 -> 3550
A7: June | B7: =C7-C6 -> 346 | C7: 989 | D7: 250 | E7: 50 | F7: =((B7-E7)*150)+(300*E7) -> 59400 | G7: =7000+(200*D7) -> 57000 | H7: =F7-G7 -> 2400
A8: July | B8: =C8-C7 -> 511 | C8: 1500 | D8: 400 | E8: 67 | F8: =((B8-E8)*150)+(480*E8) -> 98760 | G8: =7000+(200*D8) -> 87000 | H8: =F8-G8 -> 11760
A9: August | B9: =C9-C8 -> 624 | C9: 2124 | D9: 326 | E9: 100 | F9: =((B9-E9)*150)+(480*E9) -> 126600 | G9: =7000+(200*D9) -> 72200 | H9: =F9-G9 -> 54400
A10: September | B10: =C10-C9 -> 976 | C10: 3100 | D10: 669 | E10: 120 | F10: =((B10-E10)*150)+(480*E10) -> 186000 | G10: =7000+(200*D10) -> 140800 | H10: =F10-G10 -> 45200
A11: October | B11: =C11-C10 -> 1700 | C11: 4800 | D11: 1019 | E11: 200 | F11: =((B11-E11)*150)+(480*E11) -> 321000 | G11: =7000+(200*D11) -> 210800 | H11: =F11-G11 -> 110200
A12: November | B12: =C12-C11 -> 1200 | C12: 6000 | D12: 569 | E12: 250 | F12: =((B12-E12)*150)+(480*E12) -> 262500 | G12: =7000+(200*D12) -> 120800 | H12: =F12-G12 -> 141700
A13: December | B13: =C13-C12 -> 3890 | C13: 9890 | D13: 2000 | E13: 400 | F13: =((B13-E13)*150)+(480*E13) -> 715500 | G13: =7000+(200*D13) -> 407000 | H13: =F13-G13 -> 308500
A14: Total | B14: =SUM(B2:B13) -> 9890 | C14: =SUM(C2:C13) -> 30291 | D14: =SUM(D2:D13) -> 5557 | E14: =SUM(E2:E13) -> 1243 | F14: =SUM(F2:F13) -> 1874610 | G14: =SUM(G2:G13) -> 1195400 | H14: =SUM(H2:H13) -> 679210

Sheet Year 2 Forecast
A1: Month | B1: Number of Users Attracted | C1: Total Users | D1: Users attracted via adds(CPI) | E1: Subscriptions bought | F1: Revenue Generated | G1: Outflow of cash | H1: Profit
A2: January | B2: 450 | C2: 450 | D2: 250 | E2: 120 | F2: =((B2-E2)*150)+(900*E2) -> 157500 | G2: =7000+(200*D2) -> 57000 | H2: =F2-G2 -> 100500
A3: February | B3: =C3-C2 -> 200 | C3: 650 | D3: 341 | E3: 67 | F3: =((B3-E3)*150)+(900*E3) -> 80250 | G3: =7000+(200*D3) -> 75200 | H3: =F3-G3 -> 5050
A4: March | B4: =C4-C3 -> 1550 | C4: 2200 | D4: 257 | E4: 320 | F4: =((B4-E4)*150)+(900*E4) -> 472500 | G4: =7000+(200*D4) -> 58400 | H4: =F4-G4 -> 414100
A5: April | B5: =C5-C4 -> 2000 | C5: 4200 | D5: 789 | E5: 670 | F5: =((B5-E5)*150)+(900*E5) -> 802500 | G5: =7000+(200*D5) -> 164800 | H5: =F5-G5 -> 637700
A6: May | B6: =C6-C5 -> 300 | C6: 4500 | D6: 10 | E6: 596 | F6: =((B6-E6)*150)+(900*E6) -> 492000 | G6: =7000+(200*D6) -> 9000 | H6: =F6-G6 -> 483000
A7: June | B7: =C7-C6 -> 400 | C7: 4900 | D7: 250 | E7: 700 | F7: =((B7-E7)*150)+(900*E7) -> 585000 | G7: =7000+(200*D7) -> 57000 | H7: =F7-G7 -> 528000
A8: July | B8: =C8-C7 -> 2600 | C8: 7500 | D8: 1400 | E8: 970 | F8: =((B8-E8)*150)+(1100*E8) -> 1311500 | G8: =7000+(200*D8) -> 287000 | H8: =F8-G8 -> 1024500
A9: August | B9: =C9-C8 -> 4742 | C9: 12242 | D9: 2567 | E9: 1234 | F9: =((B9-E9)*150)+(1100*E9) -> 1883600 | G9: =7000+(200*D9) -> 520400 | H9: =F9-G9 -> 1363200
A10: September | B10: =C10-C9 -> 6664 | C10: 18906 | D10: 4567 | E10: 1987 | F10: =((B10-E10)*150)+(1100*E10) -> 2887250 | G10: =7000+(200*D10) -> 920400 | H10: =F10-G10 -> 1966850
A11: October | B11: =C11-C10 -> 2150 | C11: 21056 | D11: 678 | E11: 2534 | F11: =((B11-E11)*150)+(1100*E11) -> 2729800 | G11: =7000+(200*D11) -> 142600 | H11: =F11-G11 -> 2587200
A12: November | B12: =C12-C11 -> 4623 | C12: 25679 | D12: 1200 | E12: 1245 | F12: =((B12-E12)*150)+(1100*E12) -> 1876200 | G12: =7000+(200*D12) -> 247000 | H12: =F12-G12 -> 1629200
A13: December | B13: =C13-C12 -> 7313 | C13: 32992 | D13: 3567 | E13: 2987 | F13: =((B13-E13)*150)+(1100*E13) -> 3934600 | G13: =7000+(200*D13) -> 720400 | H13: =F13-G13 -> 3214200
A14: Total | B14: =SUM(B2:B13) -> 32992 | C14: =SUM(C2:C13) -> 135275 | D14: =SUM(D2:D13) -> 15876 | E14: =SUM(E2:E13) -> 13430 | F14: =SUM(F2:F13) -> 17212700 | G14: =SUM(G2:G13) -> 3259200 | H14: =SUM(H2:H13) -> 13953500

Sheet summary
B1: Total Users | C1: Subscriptions bought | D1: Total revenue | E1: Outflow | F1: Profit
A2: Year 1 | B2: ='Year 1 Forecast'!C14 -> 30291 | C2: ='Year 1 Forecast'!E14 -> 1243 | D2: ='Year 1 Forecast'!F14 -> 1874610 | E2: ='Year 1 Forecast'!G14 -> 1195400 | F2: ='Year 1 Forecast'!H14 -> 679210
A3: Year 2 | B3: ='Year 2 Forecast'!C14 -> 135275 | C3: ='Year 2 Forecast'!E14 -> 13430 | D3: ='Year 2 Forecast'!F14 -> 17212700 | E3: ='Year 2 Forecast'!G14 -> 3259200 | F3: ='Year 2 Forecast'!H14 -> 13953500
A4: Total | B4: =B2+B3 -> 165566 | C4: =C2+C3 -> 14673 | D4: =D2+D3 -> 19087310 | E4: =E2+E3 -> 4454600 | F4: =F2+F3 -> 14632710
